{
    "nb_instances": 200,
    "log_nb_instances": 5.298317366548036,
    "nb_features": 7,
    "dataset_dimensionality": 28.571428571428573,
    "log_dataset_dimensionality": 3.3524072174927233,
    "dataset_ratio": 0.035,
    "nb_missing_vals": 0,
    "ratio_features_with_missing_vals": 0.0,
    "ratio_instances_with_missing_vals": 0.0,
    "nb_numeric_features": 6,
    "nb_categorical_features": 1,
    "ratio_numeric_categorical_features": 6.0,
    "ratio_categorical_numeric_features": 0.16666666666666666,
    "nb_classes": 2,
    "class_entropy": 0.6931471805599453,
    "mean_target_class_ratio": 0.5,
    "stdev_target_class_ratio": 0.5,
    "min_target_class_ratio": 0.5,
    "median_target_class_ratio": 0.5,
    "max_target_class_ratio": 0.5,
    "mean_mean_numeric_features": 22.728668212890625,
    "stdev_mean_numeric_features": 22.728668212890625,
    "mean_stdev_numeric_features": 6.491909027099609,
    "stdev_stdev_numeric_features": 6.491909027099609,
    "mean_var_numeric_features": 58.75209045410156,
    "stdev_var_numeric_features": 58.75209045410156,
    "mean_min_numeric_features": 8.766666412353516,
    "stdev_min_numeric_features": 8.766666412353516,
    "mean_median_numeric_features": 22.774999618530273,
    "stdev_median_numeric_features": 22.774999618530273,
    "mean_max_numeric_features": 36.18333435058594,
    "stdev_max_numeric_features": 36.18333435058594,
    "mean_skew_numeric_features": -0.01907331496477127,
    "stdev_skew_numeric_features": -0.01907331496477127,
    "mean_kurtosis_numeric_features": -0.6280488967895508,
    "stdev_kurtosis_numeric_features": -0.6280488967895508,
    "pca_1": 0.9527580836066316,
    "pca_2": 0.04095455719187783,
    "pca_3": 0.003626740948948561,
    "mean_entropy_categorical_features": 0.6931471824645996,
    "stdev_entropy_categorical_features": 0.6931471824645996,
    "mean_information_gain_categorical_features": 0.0,
    "stdev_information_gain_categorical_features": 0.0,
    "mean_mutual_informaiton_categorical_features": -1.3322676295501878e-15,
    "stdev_mutual_informaiton_categorical_features": -1.3322676295501878e-15,
    "gaussian_nb_accuracy": NaN,
    "gaussian_nb_balanced_accuracy": NaN,
    "lda_accuracy": NaN,
    "lda_balanced_accuracy": NaN,
    "decision_tree_1_accuracy": NaN,
    "decision_tree_1_balanced_accuracy": NaN,
    "decision_tree_2_accuracy": NaN,
    "decision_tree_2_balanced_accuracy": NaN,
    "extra_trees_2_10_accuracy": NaN,
    "extra_trees_2_10_balanced_accuracy": NaN
}